bidsarray/__init__.py
bidsarray/component.py
bidsarray/consensus.py
bidsarray/run.py
bidsarray-0.1.1.dist-info/METADATA
bidsarray-0.1.1.dist-info/WHEEL
bidsarray-0.1.1.dist-info/entry_points.txt
bidsarray-0.1.1.dist-info/RECORD
