Metadata-Version: 2.1
Name: bidsarray
Version: 0.1.1
Summary: 
License: MIT
Author: Peter Van Dyken
Author-email: pvandyk2@uwo.ca
Requires-Python: >=3.8,<4.0
Classifier: License :: OSI Approved :: MIT License
Classifier: Operating System :: OS Independent
Classifier: Programming Language :: Python :: 3
Classifier: Programming Language :: Python :: 3.8
Classifier: Programming Language :: Python :: 3.9
Classifier: Programming Language :: Python :: 3.10
Classifier: Programming Language :: Python :: 3.11
Classifier: Programming Language :: Python :: 3.12
Requires-Dist: more-itertools (>=10.2.0,<11.0.0)
Requires-Dist: snakebids (>=0.13.1)
